README.md
setup.cfg
setup.py
shinden/__init__.py
shinden/data_objects.py
shinden/scrapping.py
shinden.egg-info/PKG-INFO
shinden.egg-info/SOURCES.txt
shinden.egg-info/dependency_links.txt
shinden.egg-info/requires.txt
shinden.egg-info/top_level.txt