Metadata-Version: 2.1
Name: shinden
Version: 0.3.4
Summary: bs4 web scrapping api for shinden.pl
Home-page: https://github.com/ShaderLight/shinden.py
Author: ShaderLight
License: MIT
Download-URL: https://github.com/ShaderLight/shinden.py/archive/v0.3.4.tar.gz
Keywords: shinden,api,web scrapping
Platform: UNKNOWN
Classifier: Development Status :: 3 - Alpha
Classifier: Intended Audience :: Developers
Classifier: License :: OSI Approved :: MIT License
Classifier: Programming Language :: Python :: 3
Classifier: Programming Language :: Python :: 3.5
Classifier: Programming Language :: Python :: 3.6
Classifier: Programming Language :: Python :: 3.7
